Metadata-Version: 2.3
Name: py-micro-model
Version: 1.0.0
Summary: gRPC model definitions for Python microservice template
Author: Noah Chalifour
Author-email: chalifournoah@gmail.com
Requires-Python: >=3.12,<4.0
Classifier: Programming Language :: Python :: 3
Classifier: Programming Language :: Python :: 3.12
Classifier: Programming Language :: Python :: 3.13
Requires-Dist: grpcio (>=1.73.0,<2.0.0)
Requires-Dist: grpcio-tools (>=1.73.0,<2.0.0)
